{"count":70,"previous_page_number":null,"current_page_number":1,"next_page_number":null,"num_pages":1,"per_page":10000,"meta":{"bbox":{"xmin":-83.77018,"ymin":10.3924,"xmax":-81.87824,"ymax":14.60287},"category":3},"results":[{"id":102824,"dt_move":"2023-12-09T10:38:52Z","point":{"type":"Point","coordinates":[-82.72375,14.60287]},"ext":"c2cb9c74e05cfdf3","fingerprint":"55b19921d4bb7e1fe7612736a4af075fc977894d","data":{"Lat":14.60287,"Lng":-82.72375,"Icon":"current","Title":"Current Location","Distance":91.6775,"Duration":72.6011,"TurtleId":373,"Collected":"December 09, 2023","Direction":"W","CollectedDateTime":"/Date(1702118332000)/"}},{"id":102769,"dt_move":"2023-12-06T10:02:48Z","point":{"type":"Point","coordinates":[-81.87824,14.50249]},"ext":"3780efeb90f3bc58","fingerprint":"8cceab72adcccba643dc174021991837d8acc040","data":{"Lat":14.50249,"Lng":-81.87824,"Icon":"current","Title":"Current Location","Distance":227.2869,"Duration":97.5497,"TurtleId":373,"Collected":"December 06, 2023","Direction":"N","CollectedDateTime":"/Date(1701856968000)/"}},{"id":102690,"dt_move":"2023-12-02T08:29:49Z","point":{"type":"Point","coordinates":[-83.25842,12.95942]},"ext":"1625fe005b616591","fingerprint":"cbd41b266166430586d48c8993716d6227a8b723","data":{"Lat":12.95942,"Lng":-83.25842,"Icon":"current","Title":"Current Location","Distance":0.4486,"Duration":22.3691,"TurtleId":373,"Collected":"December 02, 2023","Direction":"S","CollectedDateTime":"/Date(1701505789000)/"}},{"id":102672,"dt_move":"2023-12-01T10:07:40Z","point":{"type":"Point","coordinates":[-83.25647,12.96298]},"ext":"70995693cec52247","fingerprint":"f87e5a018013fd41302add6f4dea5ec88531a8ce","data":{"Lat":12.96298,"Lng":-83.25647,"Icon":"current","Title":"Current Location","Distance":16.1644,"Duration":15.2063,"TurtleId":373,"Collected":"December 01, 2023","Direction":"E","CollectedDateTime":"/Date(1701425260000)/"}},{"id":102652,"dt_move":"2023-11-30T18:55:17Z","point":{"type":"Point","coordinates":[-83.38364,12.88701]},"ext":"ffd113c5a414de87","fingerprint":"87cd9aa73134fa1a2cad23d23a7a6514e7305a10","data":{"Lat":12.88701,"Lng":-83.38364,"Icon":"current","Title":"Current Location","Distance":17.4464,"Duration":23.9805,"TurtleId":373,"Collected":"November 30, 2023","Direction":"N","CollectedDateTime":"/Date(1701370517000)/"}},{"id":102628,"dt_move":"2023-11-29T18:56:27Z","point":{"type":"Point","coordinates":[-83.33283,12.73813]},"ext":"5ae8dcb20a5c733f","fingerprint":"66f928d74e5b44ebb2800c9582afa15947b23f4b","data":{"Lat":12.73813,"Lng":-83.33283,"Icon":"current","Title":"Current Location","Distance":36.755,"Duration":104.4916,"TurtleId":373,"Collected":"November 29, 2023","Direction":"N","CollectedDateTime":"/Date(1701284187000)/"}},{"id":102540,"dt_move":"2023-11-25T10:26:57Z","point":{"type":"Point","coordinates":[-83.24668,12.41844]},"ext":"9357b086d2c15858","fingerprint":"d8197653e8751af685b4a422e70e5280305f5a5f","data":{"Lat":12.41844,"Lng":-83.24668,"Icon":"current","Title":"Current Location","Distance":8.2744,"Duration":15.1544,"TurtleId":373,"Collected":"November 25, 2023","Direction":"S","CollectedDateTime":"/Date(1700908017000)/"}},{"id":102519,"dt_move":"2023-11-24T19:17:41Z","point":{"type":"Point","coordinates":[-83.22609,12.49009]},"ext":"a7b6277a31a16d1f","fingerprint":"2839176803a6fb67fd3f82f4038b836d23ef1dc4","data":{"Lat":12.49009,"Lng":-83.22609,"Icon":"current","Title":"Current Location","Distance":20.9747,"Duration":34.2916,"TurtleId":373,"Collected":"November 24, 2023","Direction":"N","CollectedDateTime":"/Date(1700853461000)/"}},{"id":102495,"dt_move":"2023-11-23T09:00:11Z","point":{"type":"Point","coordinates":[-83.35197,12.34701]},"ext":"6b6b09b568cdd95b","fingerprint":"3194ecdb1b32919349f3f09fe8741ab8e591d5bc","data":{"Lat":12.34701,"Lng":-83.35197,"Icon":"current","Title":"Current Location","Distance":1.6688,"Duration":13.6769,"TurtleId":373,"Collected":"November 23, 2023","Direction":"N","CollectedDateTime":"/Date(1700730011000)/"}},{"id":102476,"dt_move":"2023-11-22T19:19:34Z","point":{"type":"Point","coordinates":[-83.35862,12.33348]},"ext":"615c46c50e218944","fingerprint":"2b7c82f7734ef746af4acaa0617908aea91c7648","data":{"Lat":12.33348,"Lng":-83.35862,"Icon":"current","Title":"Current Location","Distance":3.4726,"Duration":107.1572,"TurtleId":373,"Collected":"November 22, 2023","Direction":"W","CollectedDateTime":"/Date(1700680774000)/"}},{"id":102376,"dt_move":"2023-11-18T08:10:08Z","point":{"type":"Point","coordinates":[-83.3285,12.34395]},"ext":"1c277d163709756e","fingerprint":"ebfcfd7794afe3e1a76a51b719cd03b937600b71","data":{"Lat":12.34395,"Lng":-83.3285,"Icon":"current","Title":"Current Location","Distance":3.0355,"Duration":22.0633,"TurtleId":373,"Collected":"November 18, 2023","Direction":"E","CollectedDateTime":"/Date(1700295008000)/"}},{"id":102353,"dt_move":"2023-11-17T10:06:20Z","point":{"type":"Point","coordinates":[-83.35561,12.35058]},"ext":"398752d74dc70cac","fingerprint":"a1f122d4990fd731c1bf2737a9ac1ce4c8329dd2","data":{"Lat":12.35058,"Lng":-83.35561,"Icon":"current","Title":"Current Location","Distance":1.7309,"Duration":23.8658,"TurtleId":373,"Collected":"November 17, 2023","Direction":"S","CollectedDateTime":"/Date(1700215580000)/"}},{"id":102328,"dt_move":"2023-11-16T10:14:23Z","point":{"type":"Point","coordinates":[-83.36422,12.36368]},"ext":"e7496a4d5c4ff584","fingerprint":"8c73333cbd190632eb13176f2a9bc2990156445d","data":{"Lat":12.36368,"Lng":-83.36422,"Icon":"current","Title":"Current Location","Distance":8.6214,"Duration":25.4469,"TurtleId":373,"Collected":"November 16, 2023","Direction":"W","CollectedDateTime":"/Date(1700129663000)/"}},{"id":102306,"dt_move":"2023-11-15T08:47:34Z","point":{"type":"Point","coordinates":[-83.28908,12.33869]},"ext":"26f4e8481a754557","fingerprint":"4b81db879c7c463e3074c087553f6c4a453274e1","data":{"Lat":12.33869,"Lng":-83.28908,"Icon":"current","Title":"Current Location","Distance":6.0231,"Duration":23.575,"TurtleId":373,"Collected":"November 15, 2023","Direction":"E","CollectedDateTime":"/Date(1700038054000)/"}},{"id":102280,"dt_move":"2023-11-14T09:13:04Z","point":{"type":"Point","coordinates":[-83.33706,12.36585]},"ext":"7144413b35980cb2","fingerprint":"b34c95ed3ee5b154bf9cf25c195ae451ef92bc93","data":{"Lat":12.36585,"Lng":-83.33706,"Icon":"current","Title":"Current Location","Distance":8.9784,"Duration":20.4613,"TurtleId":373,"Collected":"November 14, 2023","Direction":"E","CollectedDateTime":"/Date(1699953184000)/"}},{"id":102258,"dt_move":"2023-11-13T12:45:23Z","point":{"type":"Point","coordinates":[-83.39758,12.31085]},"ext":"4e27819fe73a0cf4","fingerprint":"b3a6592c55347f813ecb6752d68592e33c921fa2","data":{"Lat":12.31085,"Lng":-83.39758,"Icon":"current","Title":"Current Location","Distance":3.4914,"Duration":27.3152,"TurtleId":373,"Collected":"November 13, 2023","Direction":"N","CollectedDateTime":"/Date(1699879523000)/"}},{"id":102232,"dt_move":"2023-11-12T09:26:28Z","point":{"type":"Point","coordinates":[-83.41767,12.28634]},"ext":"271ed52934a3ac1f","fingerprint":"366cabc51260e7e0178bca73c0e681a484c490fb","data":{"Lat":12.28634,"Lng":-83.41767,"Icon":"current","Title":"Current Location","Distance":2.6506,"Duration":10.5669,"TurtleId":373,"Collected":"November 12, 2023","Direction":"N","CollectedDateTime":"/Date(1699781188000)/"}},{"id":102211,"dt_move":"2023-11-11T22:52:27Z","point":{"type":"Point","coordinates":[-83.42738,12.26447]},"ext":"9833bcdaabd3981a","fingerprint":"25bcdd288c61daeb1abb9987df7cc596efd1522c","data":{"Lat":12.26447,"Lng":-83.42738,"Icon":"current","Title":"Current Location","Distance":8.1767,"Duration":22.7011,"TurtleId":373,"Collected":"November 11, 2023","Direction":"N","CollectedDateTime":"/Date(1699743147000)/"}},{"id":102190,"dt_move":"2023-11-11T00:10:23Z","point":{"type":"Point","coordinates":[-83.46775,12.20241]},"ext":"df8ec26ae3c5cc1c","fingerprint":"7150f43c89d4816cb182ad11834573e6a081dcf5","data":{"Lat":12.20241,"Lng":-83.46775,"Icon":"current","Title":"Current Location","Distance":11.231,"Duration":28.3955,"TurtleId":373,"Collected":"November 10, 2023","Direction":"S","CollectedDateTime":"/Date(1699661423000)/"}},{"id":101940,"dt_move":"2023-11-09T19:46:39Z","point":{"type":"Point","coordinates":[-83.40787,12.28474]},"ext":"6f5423a97bc968e3","fingerprint":"4be2ad6d6d3b52d950d9378d34adc613077137d2","data":{"Lat":12.28474,"Lng":-83.40787,"Icon":"current","Title":"Current Location","Distance":2.0966,"Duration":22.5933,"TurtleId":373,"Collected":"November 09, 2023","Direction":"S","CollectedDateTime":"/Date(1699559199000)/"}},{"id":101920,"dt_move":"2023-11-08T21:11:03Z","point":{"type":"Point","coordinates":[-83.41805,12.30076]},"ext":"711a0cb59c030fe1","fingerprint":"2080b3c454d124784d41c718a1889d31b99adedb","data":{"Lat":12.30076,"Lng":-83.41805,"Icon":"current","Title":"Current Location","Distance":9.2498,"Duration":31.788,"TurtleId":373,"Collected":"November 08, 2023","Direction":"S","CollectedDateTime":"/Date(1699477863000)/"}},{"id":101896,"dt_move":"2023-11-07T13:23:46Z","point":{"type":"Point","coordinates":[-83.41172,12.38372]},"ext":"329792fb484881e2","fingerprint":"f497bef96fe16a83451128565224a4f2d2902098","data":{"Lat":12.38372,"Lng":-83.41172,"Icon":"current","Title":"Current Location","Distance":5.2161,"Duration":27.8033,"TurtleId":373,"Collected":"November 07, 2023","Direction":"N","CollectedDateTime":"/Date(1699363426000)/"}},{"id":101865,"dt_move":"2023-11-06T09:35:34Z","point":{"type":"Point","coordinates":[-83.38234,12.34661]},"ext":"313a02063d8c97b2","fingerprint":"9e5bb3259d4a4dc47c1659102a08459b721c917c","data":{"Lat":12.34661,"Lng":-83.38234,"Icon":"current","Title":"Current Location","Distance":7.5649,"Duration":24.633,"TurtleId":373,"Collected":"November 06, 2023","Direction":"S","CollectedDateTime":"/Date(1699263334000)/"}},{"id":101841,"dt_move":"2023-11-05T07:57:35Z","point":{"type":"Point","coordinates":[-83.34192,12.40202]},"ext":"b1e9528b4e149b45","fingerprint":"23dd64c85356136eff901040c0934f70e4b187f3","data":{"Lat":12.40202,"Lng":-83.34192,"Icon":"current","Title":"Current Location","Distance":2.143,"Duration":18.9777,"TurtleId":373,"Collected":"November 05, 2023","Direction":"N","CollectedDateTime":"/Date(1699171055000)/"}},{"id":101821,"dt_move":"2023-11-04T12:58:55Z","point":{"type":"Point","coordinates":[-83.35404,12.38681]},"ext":"aea89b1de4733c48","fingerprint":"a40daf4dea5036c5756e994268f331fe67e13f8f","data":{"Lat":12.38681,"Lng":-83.35404,"Icon":"current","Title":"Current Location","Distance":3.0332,"Duration":28.4566,"TurtleId":373,"Collected":"November 04, 2023","Direction":"N","CollectedDateTime":"/Date(1699102735000)/"}},{"id":101790,"dt_move":"2023-11-03T08:31:31Z","point":{"type":"Point","coordinates":[-83.36352,12.36115]},"ext":"6fe96addd7715dee","fingerprint":"2e5ae5bb3b8b7094a1ad9f7352ec625fbfc85c78","data":{"Lat":12.36115,"Lng":-83.36352,"Icon":"current","Title":"Current Location","Distance":3.4945,"Duration":24.6944,"TurtleId":373,"Collected":"November 03, 2023","Direction":"E","CollectedDateTime":"/Date(1699000291000)/"}},{"id":101789,"dt_move":"2023-11-02T07:49:51Z","point":{"type":"Point","coordinates":[-83.38774,12.38184]},"ext":"133cfc572aa498e4","fingerprint":"7e0986d548767a3c3689373a3f8e3ead0686bd8d","data":{"Lat":12.38184,"Lng":-83.38774,"Icon":"location","Title":"","Distance":7.7512,"Duration":22.9055,"TurtleId":373,"Collected":"November 02, 2023","Direction":"W","CollectedDateTime":"/Date(1698911391000)/"}},{"id":101747,"dt_move":"2023-11-01T08:55:31Z","point":{"type":"Point","coordinates":[-83.32994,12.34095]},"ext":"f63c96534c6a6c1b","fingerprint":"3d606e18ee023e507457b7de3b1daf53b84a2c44","data":{"Lat":12.34095,"Lng":-83.32994,"Icon":"current","Title":"Current Location","Distance":1.6606,"Duration":24.0072,"TurtleId":373,"Collected":"November 01, 2023","Direction":"E","CollectedDateTime":"/Date(1698828931000)/"}},{"id":101726,"dt_move":"2023-10-31T08:55:05Z","point":{"type":"Point","coordinates":[-83.34304,12.33325]},"ext":"ec461bd9a971a574","fingerprint":"1dbad3027a7bd278290f2031f20efff2b5d5bcd2","data":{"Lat":12.33325,"Lng":-83.34304,"Icon":"current","Title":"Current Location","Distance":1.3345,"Duration":24.6083,"TurtleId":373,"Collected":"October 31, 2023","Direction":"W","CollectedDateTime":"/Date(1698742505000)/"}},{"id":101699,"dt_move":"2023-10-30T08:18:35Z","point":{"type":"Point","coordinates":[-83.33298,12.34014]},"ext":"9a25062bd3558d8e","fingerprint":"ea338424e8d622315bfc21e4948ee71a06b0ee90","data":{"Lat":12.34014,"Lng":-83.33298,"Icon":"current","Title":"Current Location","Distance":1.3759,"Duration":23.4536,"TurtleId":373,"Collected":"October 30, 2023","Direction":"W","CollectedDateTime":"/Date(1698653915000)/"}},{"id":101673,"dt_move":"2023-10-29T08:51:22Z","point":{"type":"Point","coordinates":[-83.32292,12.34766]},"ext":"0c6caa98966f88b2","fingerprint":"bf95a7c1f37fd47f0a403bd7464debcf0bd0d192","data":{"Lat":12.34766,"Lng":-83.32292,"Icon":"current","Title":"Current Location","Distance":5.4435,"Duration":25.7955,"TurtleId":373,"Collected":"October 29, 2023","Direction":"N","CollectedDateTime":"/Date(1698569482000)/"}},{"id":101652,"dt_move":"2023-10-28T07:03:38Z","point":{"type":"Point","coordinates":[-83.28995,12.31079]},"ext":"64a278c73dbdaf59","fingerprint":"682c8c1a0033cffdaa2a709e77569a4de1455569","data":{"Lat":12.31079,"Lng":-83.28995,"Icon":"current","Title":"Current Location","Distance":7.9017,"Duration":21.5163,"TurtleId":373,"Collected":"October 28, 2023","Direction":"S","CollectedDateTime":"/Date(1698476618000)/"}},{"id":101630,"dt_move":"2023-10-27T09:32:39Z","point":{"type":"Point","coordinates":[-83.31778,12.37645]},"ext":"7ac09be2494a8d2d","fingerprint":"7617e6049161ca78d0215d0583542dd4151588c0","data":{"Lat":12.37645,"Lng":-83.31778,"Icon":"current","Title":"Current Location","Distance":3.0934,"Duration":25.0925,"TurtleId":373,"Collected":"October 27, 2023","Direction":"N","CollectedDateTime":"/Date(1698399159000)/"}},{"id":101603,"dt_move":"2023-10-26T08:27:06Z","point":{"type":"Point","coordinates":[-83.3291,12.35092]},"ext":"17b876fab2ee9ecd","fingerprint":"4b6e524ecb59ce8e411ffd96666375e5ad712965","data":{"Lat":12.35092,"Lng":-83.3291,"Icon":"current","Title":"Current Location","Distance":0.9101,"Duration":25.3586,"TurtleId":373,"Collected":"October 26, 2023","Direction":"N","CollectedDateTime":"/Date(1698308826000)/"}},{"id":101577,"dt_move":"2023-10-25T07:05:35Z","point":{"type":"Point","coordinates":[-83.33293,12.34364]},"ext":"2b896010905e046c","fingerprint":"17d967ac1ba5361951efaeb1dace044c1437b2ca","data":{"Lat":12.34364,"Lng":-83.33293,"Icon":"current","Title":"Current Location","Distance":6.9496,"Duration":21.8569,"TurtleId":373,"Collected":"October 25, 2023","Direction":"W","CollectedDateTime":"/Date(1698217535000)/"}},{"id":101550,"dt_move":"2023-10-24T09:14:10Z","point":{"type":"Point","coordinates":[-83.27461,12.31794]},"ext":"164375d20bfae6e1","fingerprint":"7c810a72b214d24a1429b4973186f30572ef8d8a","data":{"Lat":12.31794,"Lng":-83.27461,"Icon":"current","Title":"Current Location","Distance":5.5551,"Duration":25.8491,"TurtleId":373,"Collected":"October 24, 2023","Direction":"N","CollectedDateTime":"/Date(1698138850000)/"}},{"id":101526,"dt_move":"2023-10-23T07:23:13Z","point":{"type":"Point","coordinates":[-83.26205,12.26951]},"ext":"17423876d7b240d9","fingerprint":"c4a0be683c86629beb9f47193b4b84062cf457aa","data":{"Lat":12.26951,"Lng":-83.26205,"Icon":"current","Title":"Current Location","Distance":6.3085,"Duration":23.8486,"TurtleId":373,"Collected":"October 23, 2023","Direction":"S","CollectedDateTime":"/Date(1698045793000)/"}},{"id":101500,"dt_move":"2023-10-22T07:32:18Z","point":{"type":"Point","coordinates":[-83.30221,12.31049]},"ext":"212126d286f9ad9d","fingerprint":"62e723a8ef611a583bf92cbe3f82eb294de17493","data":{"Lat":12.31049,"Lng":-83.30221,"Icon":"current","Title":"Current Location","Distance":8.9915,"Duration":21.6847,"TurtleId":373,"Collected":"October 22, 2023","Direction":"S","CollectedDateTime":"/Date(1697959938000)/"}},{"id":101478,"dt_move":"2023-10-21T09:51:13Z","point":{"type":"Point","coordinates":[-83.34123,12.38181]},"ext":"9c206b3916401441","fingerprint":"99d4f2b1e290a91169a9388d1978baa52d838b56","data":{"Lat":12.38181,"Lng":-83.34123,"Icon":"current","Title":"Current Location","Distance":2.8288,"Duration":26.2444,"TurtleId":373,"Collected":"October 21, 2023","Direction":"W","CollectedDateTime":"/Date(1697881873000)/"}},{"id":101450,"dt_move":"2023-10-20T07:36:33Z","point":{"type":"Point","coordinates":[-83.31829,12.36976]},"ext":"2508f9f51a0cc9ea","fingerprint":"7c2dcbfee3feeaf68da8f46177ca5c1126db9a6c","data":{"Lat":12.36976,"Lng":-83.31829,"Icon":"current","Title":"Current Location","Distance":7.2574,"Duration":22.0111,"TurtleId":373,"Collected":"October 20, 2023","Direction":"E","CollectedDateTime":"/Date(1697787393000)/"}},{"id":101424,"dt_move":"2023-10-19T09:35:53Z","point":{"type":"Point","coordinates":[-83.38511,12.37034]},"ext":"5cbc27413af754e2","fingerprint":"743e96bdcf102a2508f651eb1368e2991a1384e0","data":{"Lat":12.37034,"Lng":-83.38511,"Icon":"current","Title":"Current Location","Distance":4.2493,"Duration":25.1208,"TurtleId":373,"Collected":"October 19, 2023","Direction":"N","CollectedDateTime":"/Date(1697708153000)/"}},{"id":101397,"dt_move":"2023-10-18T08:28:38Z","point":{"type":"Point","coordinates":[-83.40137,12.33558]},"ext":"d386580e8e9a4e0b","fingerprint":"48047ed4df1e743d3b2b3a79b164a6ee1e41e6fd","data":{"Lat":12.33558,"Lng":-83.40137,"Icon":"current","Title":"Current Location","Distance":10.0707,"Duration":25.1236,"TurtleId":373,"Collected":"October 18, 2023","Direction":"W","CollectedDateTime":"/Date(1697617718000)/"}},{"id":101351,"dt_move":"2023-10-17T07:21:13Z","point":{"type":"Point","coordinates":[-83.30903,12.34371]},"ext":"2ec7384614d0bb1d","fingerprint":"a36f8206888dfd9e6c9aeb8668ed04bd43d617de","data":{"Lat":12.34371,"Lng":-83.30903,"Icon":"current","Title":"Current Location","Distance":2.3372,"Duration":23.7286,"TurtleId":373,"Collected":"October 17, 2023","Direction":"E","CollectedDateTime":"/Date(1697527273000)/"}},{"id":101350,"dt_move":"2023-10-16T07:37:30Z","point":{"type":"Point","coordinates":[-83.3285,12.35266]},"ext":"a06177cc3a757472","fingerprint":"d23a15ce9fb156c173946578efc0d8d775105fc7","data":{"Lat":12.35266,"Lng":-83.3285,"Icon":"location","Title":"","Distance":5.7063,"Duration":24.3944,"TurtleId":373,"Collected":"October 16, 2023","Direction":"W","CollectedDateTime":"/Date(1697441850000)/"}},{"id":101349,"dt_move":"2023-10-15T07:13:50Z","point":{"type":"Point","coordinates":[-83.28604,12.32244]},"ext":"c4bbb7dd73b1efb9","fingerprint":"4269b18aaeef6145806c9994a8ea1fed06daca90","data":{"Lat":12.32244,"Lng":-83.28604,"Icon":"location","Title":"","Distance":6.9703,"Duration":23.7377,"TurtleId":373,"Collected":"October 15, 2023","Direction":"E","CollectedDateTime":"/Date(1697354030000)/"}},{"id":101348,"dt_move":"2023-10-14T07:29:34Z","point":{"type":"Point","coordinates":[-83.34046,12.35566]},"ext":"bcb114fc6874213e","fingerprint":"d6b36139b01f2a95c3a81ac86b1e8306f43b8c77","data":{"Lat":12.35566,"Lng":-83.34046,"Icon":"location","Title":"","Distance":3.7796,"Duration":21.81,"TurtleId":373,"Collected":"October 14, 2023","Direction":"N","CollectedDateTime":"/Date(1697268574000)/"}},{"id":101347,"dt_move":"2023-10-13T09:40:58Z","point":{"type":"Point","coordinates":[-83.32009,12.3281]},"ext":"11b286cdda5db883","fingerprint":"c228e6465ddbd89df7440e4cb706be9521acf6d1","data":{"Lat":12.3281,"Lng":-83.32009,"Icon":"location","Title":"","Distance":5.6222,"Duration":26.0961,"TurtleId":373,"Collected":"October 13, 2023","Direction":"W","CollectedDateTime":"/Date(1697190058000)/"}},{"id":101346,"dt_move":"2023-10-12T07:35:12Z","point":{"type":"Point","coordinates":[-83.2773,12.35655]},"ext":"4663ed48c22771a9","fingerprint":"a113c37ec1dba1419da57afe67f15b5dee50d366","data":{"Lat":12.35655,"Lng":-83.2773,"Icon":"location","Title":"","Distance":6.6748,"Duration":21.758,"TurtleId":373,"Collected":"October 12, 2023","Direction":"E","CollectedDateTime":"/Date(1697096112000)/"}},{"id":101218,"dt_move":"2023-10-11T09:49:43Z","point":{"type":"Point","coordinates":[-83.33433,12.33419]},"ext":"43a104d41527df73","fingerprint":"ff54107ba203807eb0552538a3939692d398389f","data":{"Lat":12.33419,"Lng":-83.33433,"Icon":"current","Title":"Current Location","Distance":5.1065,"Duration":25.5527,"TurtleId":373,"Collected":"October 11, 2023","Direction":"E","CollectedDateTime":"/Date(1697017783000)/"}},{"id":101193,"dt_move":"2023-10-10T08:16:33Z","point":{"type":"Point","coordinates":[-83.38115,12.33005]},"ext":"efcc62b0f96120dc","fingerprint":"55fd1df06dff6aef9f4e444ac47be752c67926d4","data":{"Lat":12.33005,"Lng":-83.38115,"Icon":"current","Title":"Current Location","Distance":7.6036,"Duration":25.25,"TurtleId":373,"Collected":"October 10, 2023","Direction":"W","CollectedDateTime":"/Date(1696925793000)/"}},{"id":101167,"dt_move":"2023-10-09T07:01:33Z","point":{"type":"Point","coordinates":[-83.31991,12.36318]},"ext":"2d94f8059a1ab74a","fingerprint":"5248601936eaabba3fa49f5236fdbd52972aa8da","data":{"Lat":12.36318,"Lng":-83.31991,"Icon":"current","Title":"Current Location","Distance":12.5585,"Duration":23.4263,"TurtleId":373,"Collected":"October 09, 2023","Direction":"N","CollectedDateTime":"/Date(1696834893000)/"}},{"id":101142,"dt_move":"2023-10-08T07:35:58Z","point":{"type":"Point","coordinates":[-83.39465,12.27701]},"ext":"e92b6decd6b2c2b3","fingerprint":"08798d196b0ec2b6c0afcb7dd29ab431a579508e","data":{"Lat":12.27701,"Lng":-83.39465,"Icon":"current","Title":"Current Location","Distance":2.6502,"Duration":23.5163,"TurtleId":373,"Collected":"October 08, 2023","Direction":"S","CollectedDateTime":"/Date(1696750558000)/"}},{"id":101117,"dt_move":"2023-10-07T08:04:59Z","point":{"type":"Point","coordinates":[-83.40578,12.29822]},"ext":"78a3200f54af8d4c","fingerprint":"7486d5d369b1a623608dac66322be3dad46bd927","data":{"Lat":12.29822,"Lng":-83.40578,"Icon":"current","Title":"Current Location","Distance":10.5631,"Duration":23.5583,"TurtleId":373,"Collected":"October 07, 2023","Direction":"E","CollectedDateTime":"/Date(1696665899000)/"}},{"id":101090,"dt_move":"2023-10-06T08:31:29Z","point":{"type":"Point","coordinates":[-83.48433,12.24224]},"ext":"a2d751894a84d7b2","fingerprint":"5c2c1729a4d152b223d3639779aa0fa60c78c688","data":{"Lat":12.24224,"Lng":-83.48433,"Icon":"current","Title":"Current Location","Distance":5.6269,"Duration":25.0972,"TurtleId":373,"Collected":"October 06, 2023","Direction":"W","CollectedDateTime":"/Date(1696581089000)/"}},{"id":101064,"dt_move":"2023-10-05T07:25:39Z","point":{"type":"Point","coordinates":[-83.44304,12.2117]},"ext":"262fed3318b9e47f","fingerprint":"e91819a751ece46e731606e9701c6748caaf9010","data":{"Lat":12.2117,"Lng":-83.44304,"Icon":"current","Title":"Current Location","Distance":9.4472,"Duration":22.48,"TurtleId":373,"Collected":"October 05, 2023","Direction":"E","CollectedDateTime":"/Date(1696490739000)/"}},{"id":101041,"dt_move":"2023-10-04T08:56:51Z","point":{"type":"Point","coordinates":[-83.52994,12.21403]},"ext":"73bb66f636298a74","fingerprint":"4667a6f871a7169d7484ebb463b6687434893ce5","data":{"Lat":12.21403,"Lng":-83.52994,"Icon":"current","Title":"Current Location","Distance":1.6489,"Duration":25.8377,"TurtleId":373,"Collected":"October 04, 2023","Direction":"N","CollectedDateTime":"/Date(1696409811000)/"}},{"id":101018,"dt_move":"2023-10-03T07:06:35Z","point":{"type":"Point","coordinates":[-83.53331,12.19957]},"ext":"f0c2b7e0f4dbe776","fingerprint":"cfd1179787b63d6b2514801c1c5a07d9cc174901","data":{"Lat":12.19957,"Lng":-83.53331,"Icon":"current","Title":"Current Location","Distance":5.8087,"Duration":23.643,"TurtleId":373,"Collected":"October 03, 2023","Direction":"S","CollectedDateTime":"/Date(1696316795000)/"}},{"id":100991,"dt_move":"2023-10-02T07:28:00Z","point":{"type":"Point","coordinates":[-83.56041,12.2446]},"ext":"dc3078f42a3930fe","fingerprint":"67a4945bc6bba02bd59f48535baa2e750c070009","data":{"Lat":12.2446,"Lng":-83.56041,"Icon":"current","Title":"Current Location","Distance":12.0293,"Duration":23.048,"TurtleId":373,"Collected":"October 02, 2023","Direction":"W","CollectedDateTime":"/Date(1696231680000)/"}},{"id":100961,"dt_move":"2023-10-01T08:25:07Z","point":{"type":"Point","coordinates":[-83.45886,12.2877]},"ext":"160272c99964c03e","fingerprint":"de4a8b6019f20adf108a2262885358eecd5f835e","data":{"Lat":12.2877,"Lng":-83.45886,"Icon":"current","Title":"Current Location","Distance":1.0206,"Duration":25.0527,"TurtleId":373,"Collected":"October 01, 2023","Direction":"S","CollectedDateTime":"/Date(1696148707000)/"}},{"id":100934,"dt_move":"2023-09-30T07:21:57Z","point":{"type":"Point","coordinates":[-83.46043,12.29675]},"ext":"ea9d17e044e38744","fingerprint":"a5eac51f7dd78a4e4da0fcb5498d4e4934a85aa9","data":{"Lat":12.29675,"Lng":-83.46043,"Icon":"current","Title":"Current Location","Distance":7.3851,"Duration":24.1183,"TurtleId":373,"Collected":"September 30, 2023","Direction":"N","CollectedDateTime":"/Date(1696058517000)/"}},{"id":100884,"dt_move":"2023-09-29T07:14:51Z","point":{"type":"Point","coordinates":[-83.45102,12.23097]},"ext":"496d2e5414925bab","fingerprint":"31013895893290fbffa9b75c6bdc218b66d870c0","data":{"Lat":12.23097,"Lng":-83.45102,"Icon":"current","Title":"Current Location","Distance":8.1643,"Duration":24.1905,"TurtleId":373,"Collected":"September 29, 2023","Direction":"E","CollectedDateTime":"/Date(1695971691000)/"}},{"id":100883,"dt_move":"2023-09-28T07:03:25Z","point":{"type":"Point","coordinates":[-83.50773,12.18281]},"ext":"cccd4cc7550bb0d0","fingerprint":"90d02ba1841eaec946ffae2abd7a5140afa0f523","data":{"Lat":12.18281,"Lng":-83.50773,"Icon":"location","Title":"","Distance":31.7055,"Duration":23.6302,"TurtleId":373,"Collected":"September 28, 2023","Direction":"N","CollectedDateTime":"/Date(1695884605000)/"}},{"id":100882,"dt_move":"2023-09-27T07:25:36Z","point":{"type":"Point","coordinates":[-83.59641,11.91117]},"ext":"b4871527ad24655e","fingerprint":"b4ca90795c093f3f9b6c392d037ef8a70f1f3c03","data":{"Lat":11.91117,"Lng":-83.59641,"Icon":"location","Title":"","Distance":27.5687,"Duration":24.0747,"TurtleId":373,"Collected":"September 27, 2023","Direction":"N","CollectedDateTime":"/Date(1695799536000)/"}},{"id":100881,"dt_move":"2023-09-26T07:21:07Z","point":{"type":"Point","coordinates":[-83.61614,11.66398]},"ext":"b7ed69e353f8387d","fingerprint":"fc9bccf775172bce6441ebc9d3be1e740b2b0bbb","data":{"Lat":11.66398,"Lng":-83.61614,"Icon":"location","Title":"","Distance":39.8349,"Duration":23.6238,"TurtleId":373,"Collected":"September 26, 2023","Direction":"N","CollectedDateTime":"/Date(1695712867000)/"}},{"id":100880,"dt_move":"2023-09-25T07:43:41Z","point":{"type":"Point","coordinates":[-83.77018,11.33907]},"ext":"0e90163eca438ad4","fingerprint":"62ed4d64ab907a6e06bf2b7ea33bd226832b658b","data":{"Lat":11.33907,"Lng":-83.77018,"Icon":"location","Title":"","Distance":46.929,"Duration":23.5027,"TurtleId":373,"Collected":"September 25, 2023","Direction":"N","CollectedDateTime":"/Date(1695627821000)/"}},{"id":100879,"dt_move":"2023-09-24T08:13:31Z","point":{"type":"Point","coordinates":[-83.66967,10.92869]},"ext":"042833349bc1d1b0","fingerprint":"d62f151a2d1c8164ff1a9f676b0d7959fbdb6004","data":{"Lat":10.92869,"Lng":-83.66967,"Icon":"location","Title":"","Distance":34.4489,"Duration":25.078,"TurtleId":373,"Collected":"September 24, 2023","Direction":"N","CollectedDateTime":"/Date(1695543211000)/"}},{"id":100878,"dt_move":"2023-09-23T07:08:50Z","point":{"type":"Point","coordinates":[-83.51769,10.65721]},"ext":"790b0846e3748427","fingerprint":"81f2c23f293a38184a974a0b0c478f31ca9085a3","data":{"Lat":10.65721,"Lng":-83.51769,"Icon":"location","Title":"","Distance":27.7763,"Duration":22.9805,"TurtleId":373,"Collected":"September 23, 2023","Direction":"N","CollectedDateTime":"/Date(1695452930000)/"}},{"id":100877,"dt_move":"2023-09-22T08:10:00Z","point":{"type":"Point","coordinates":[-83.4042,10.4337]},"ext":"9046eb5497f85d4f","fingerprint":"66218b59f9da27d755bf066f32df105a035169fb","data":{"Lat":10.4337,"Lng":-83.4042,"Icon":"location","Title":"","Distance":2.9084,"Duration":14.6688,"TurtleId":373,"Collected":"September 22, 2023","Direction":"E","CollectedDateTime":"/Date(1695370200000)/"}},{"id":100876,"dt_move":"2023-09-21T17:29:52Z","point":{"type":"Point","coordinates":[-83.42947,10.42554]},"ext":"3779a22e86fa3f21","fingerprint":"9ea343b2b0a8fc79c364e8df1de11b506a1c141e","data":{"Lat":10.42554,"Lng":-83.42947,"Icon":"location","Title":"","Distance":3.8889,"Duration":17.8644,"TurtleId":373,"Collected":"September 21, 2023","Direction":"N","CollectedDateTime":"/Date(1695317392000)/"}},{"id":100875,"dt_move":"2023-09-20T23:38:00Z","point":{"type":"Point","coordinates":[-83.4181,10.3924]},"ext":"8b67552a35bc1a57","fingerprint":"e3b0c44298fc1c149afbf4c8996fb92427ae41e4","data":{"Lat":10.3924,"Lng":-83.4181,"Icon":"start","Title":"Release Site","Distance":null,"Duration":null,"TurtleId":373,"Collected":"September 20, 2023","Direction":"N","CollectedDateTime":"/Date(1695253080000)/"}}]}